importo/__init__.py
importo/__main__.py
importo/parser.py
importo/profiler.py
importo/utils.py
importo-0.2.1.dist-info/METADATA
importo-0.2.1.dist-info/WHEEL
importo-0.2.1.dist-info/entry_points.txt
importo-0.2.1.dist-info/RECORD
