Metadata-Version: 2.4
Name: importo
Version: 0.2.1
Summary: Python import time profiler.
Author: Joao Figueiredo
Maintainer: Joao Figueiredo
Requires-Python: >=3.9
